fastapi_backend_template/__init__.py
fastapi_backend_template/cli.py
fastapi_backend_template/template/backend/Dockerfile
fastapi_backend_template/template/backend/README.md
fastapi_backend_template/template/backend/alembic.ini
fastapi_backend_template/template/backend/app.py
fastapi_backend_template/template/backend/entrypoint.sh
fastapi_backend_template/template/backend/pyproject.toml
fastapi_backend_template/template/backend/requirements.txt
fastapi_backend_template/template/backend/src/__init__.py
fastapi_backend_template/template/backend/src/main.py
fastapi_backend_template/template/backend/src/api/__init__.py
fastapi_backend_template/template/backend/src/api/endpoints.py
fastapi_backend_template/template/backend/src/api/dependencies/__init__.py
fastapi_backend_template/template/backend/src/api/dependencies/repository.py
fastapi_backend_template/template/backend/src/api/dependencies/response.py
fastapi_backend_template/template/backend/src/api/dependencies/session.py
fastapi_backend_template/template/backend/src/api/routes/__init__.py
fastapi_backend_template/template/backend/src/api/routes/account.py
fastapi_backend_template/template/backend/src/api/routes/authentication.py
fastapi_backend_template/template/backend/src/config/__init__.py
fastapi_backend_template/template/backend/src/config/events.py
fastapi_backend_template/template/backend/src/config/manager.py
fastapi_backend_template/template/backend/src/config/settings/__init__.py
fastapi_backend_template/template/backend/src/config/settings/base.py
fastapi_backend_template/template/backend/src/config/settings/development.py
fastapi_backend_template/template/backend/src/config/settings/environment.py
fastapi_backend_template/template/backend/src/config/settings/production.py
fastapi_backend_template/template/backend/src/config/settings/staging.py
fastapi_backend_template/template/backend/src/models/__init__.py
fastapi_backend_template/template/backend/src/models/db/__init__.py
fastapi_backend_template-0.1.9.dist-info/licenses/LICENSE
fastapi_backend_template-0.1.9.dist-info/licenses/LICENSE.md
fastapi_backend_template-0.1.9.dist-info/METADATA
fastapi_backend_template-0.1.9.dist-info/WHEEL
fastapi_backend_template-0.1.9.dist-info/entry_points.txt
fastapi_backend_template-0.1.9.dist-info/top_level.txt
fastapi_backend_template-0.1.9.dist-info/RECORD
