Metadata-Version: 2.4
Name: fastapi-backend-template
Version: 0.1.9
Summary: 快速创建基于FastAPI的后端项目的脚手架工具
Author-email: Gavin Cui <gavincui1026@gmail.com>
License: MIT
Project-URL: Homepage, https://github.com/gavincui1026/Fastapi-Backend.git
Project-URL: Issues, https://github.com/gavincui1026/Fastapi-Backend/issues
Project-URL: Documentation, https://github.com/gavincui1026/Fastapi-Backend#readme
Keywords: fastapi,backend,template,scaffold,generator
Classifier: Development Status :: 3 - Alpha
Classifier: Intended Audience :: Developers
Classifier: License :: OSI Approved :: MIT License
Classifier: Programming Language :: Python :: 3
Classifier: Programming Language :: Python :: 3.9
Classifier: Programming Language :: Python :: 3.10
Classifier: Programming Language :: Python :: 3.11
Classifier: Programming Language :: Python :: 3.12
Classifier: Topic :: Software Development :: Code Generators
Classifier: Topic :: Software Development :: Libraries :: Application Frameworks
Requires-Python: >=3.9
Requires-Dist: fastapi>=0.104.1
Requires-Dist: pydantic>=2.5.2
Requires-Dist: pydantic-settings>=2.1.0
Requires-Dist: setuptools>=65.0.0
Requires-Dist: uvicorn>=0.24.0
Requires-Dist: python-decouple>=3.8
Requires-Dist: email-validator>=2.1.0
Requires-Dist: sqlalchemy>=2.0.23
Requires-Dist: alembic>=1.12.1
Requires-Dist: aiomysql>=0.2.0
Requires-Dist: cryptography>=41.0.5
Requires-Dist: python-jose>=3.3.0
Requires-Dist: passlib>=1.7.4
Requires-Dist: bcrypt>=4.0.1
Requires-Dist: argon2-cffi>=23.1.0
Requires-Dist: loguru>=0.7.2
Requires-Dist: python-multipart>=0.0.6
Requires-Dist: rich>=13.6.0
